{
  "repos": [
    {
      "url": "https://github.com/borisyankov/DefinitelyTyped.git",
      "ref": "master"
    }
  ],
  "path": "typings",
  "bundle": "typings/bundle.d.ts",
  "link": {
    "npm": {
      "include": true
    }
  },
  "dependencies": {
    "source-map-support/source-map-support.d.ts": {
      "ref": "30387ec3dd6eb426cc48522fd3aef09ada83aa48"
    },
    "mocha/mocha.d.ts": {
      "ref": "6436105ed9e3f9de49ca7e2e010ffe298e884e40"
    },
    "chai/chai.d.ts": {
      "ref": "6436105ed9e3f9de49ca7e2e010ffe298e884e40"
    }
  }
}